hashstorage/__init__.py
hashstorage/cli.py
hashstorage/hashstorage.py
hashstorage/utils.py
hashstorage-0.1.2.dist-info/entry_points.txt
hashstorage-0.1.2.dist-info/WHEEL
hashstorage-0.1.2.dist-info/METADATA
hashstorage-0.1.2.dist-info/RECORD
